3dgs_edit_tools-0.3.0.dist-info/licenses/LICENSE
src/__init__.py
src/color_utils.py
src/compare_gs.py
src/compare_utils.py
src/csv_to_gs.py
src/file_utils.py
src/gs_to_csv.py
src/gs_to_mesh.py
src/gs_to_pointcloud.py
src/merge_gs.py
src/mesh_utils.py
src/pointcloud_to_csv.py
src/pointcloud_to_gs.py
src/pointcloud_to_mesh.py
src/transform_utils.py
src/utils.py
3dgs_edit_tools-0.3.0.dist-info/METADATA
3dgs_edit_tools-0.3.0.dist-info/WHEEL
3dgs_edit_tools-0.3.0.dist-info/entry_points.txt
3dgs_edit_tools-0.3.0.dist-info/top_level.txt
3dgs_edit_tools-0.3.0.dist-info/RECORD
