Metadata-Version: 2.4
Name: 3dgs-edit-tools
Version: 0.3.0
Summary: A Python library to convert, edit, and manage 3D Gaussian Splatting data
Home-page: https://github.com/404background/3dgs-edit-tools
Author: 404background
Author-email: 404background <404background@gmail.com>
License: MIT
Project-URL: Homepage, https://github.com/404background/3dgs-edit-tools
Project-URL: Bug Tracker, https://github.com/404background/3dgs-edit-tools/issues
Classifier: Programming Language :: Python :: 3
Classifier: License :: OSI Approved :: MIT License
Classifier: Operating System :: OS Independent
Requires-Python: >=3.6
License-File: LICENSE
Requires-Dist: numpy
Provides-Extra: tools
Requires-Dist: pandas; extra == "tools"
Requires-Dist: matplotlib; extra == "tools"
Provides-Extra: mesh
Requires-Dist: open3d; extra == "mesh"
Provides-Extra: visualization
Requires-Dist: pandas; extra == "visualization"
Requires-Dist: matplotlib; extra == "visualization"
Dynamic: author
Dynamic: home-page
Dynamic: license-file
Dynamic: requires-python
